my_package/__init__.py
my_package/my_code.py
ste2_my_fab_project-0.0.2.dist-info/METADATA
ste2_my_fab_project-0.0.2.dist-info/WHEEL
ste2_my_fab_project-0.0.2.dist-info/top_level.txt
ste2_my_fab_project-0.0.2.dist-info/RECORD
