Metadata-Version: 2.1
Name: ste2-my-fab-project
Version: 0.0.2
Summary: Simple code example
Requires-Dist: certifi ==2024.2.2
Requires-Dist: charset-normalizer ==3.3.2
Requires-Dist: idna ==3.6
Requires-Dist: pip ==24.0
Requires-Dist: requests ==2.31.0
Requires-Dist: setuptools ==69.0.3
Requires-Dist: urllib3 ==2.2.0
